Metadata-Version: 2.1
Name: avimu-probability
Version: 1.0
Summary: Binomial and Gaussian distributions
Author: Avi Mukesh
License: UNKNOWN
Platform: UNKNOWN
